{
    "MinAppearanceDate": "2598-01-01T00:00:00Z",
    "MechTags": {
        "items": [
            "unit_release",
            "unit_mech",
            "unit_medium",
            "unit_range_medium",
            "unit_lance_skirmisher",
            "unit_lance_assassin",
            "unit_role_flanker",
            "unit_armor_high",
            "unit_hot",
            "NotDavion",
            "NotLiao",
            "NotMarik",
            "NotSteiner",
            "Kurita",
            "NotMagistracyOfCanopus",
            "NotTaurianConcordat",
            "NotLocals",
            "NotAuriganRestoration",
            "NotComStar",
            "NotMercenaryReviewBoard",
            "NotAuriganPirates",
            "NotAuriganMercenaries"
        ],
        "tagSetSourceFile": ""
    },
    "inventory": [
        {
            "MountedLocation": "Head",
            "ComponentDefID": "Weapon_Laser_MediumLaser_0-STOCK",
            "ComponentDefType": "Weapon",
            "HardpointSlot": 0,
            "DamageLevel": "Functional"
        },
        {
            "MountedLocation": "LeftTorso",
            "ComponentDefID": "Weapon_SRM_SRM6_0-STOCK",
            "ComponentDefType": "Weapon",
            "HardpointSlot": 0,
            "DamageLevel": "Functional"
        },
        {
            "MountedLocation": "CenterTorso",
            "ComponentDefID": "Gear_HeatSink_Generic_Standard",
            "ComponentDefType": "HeatSink",
            "HardpointSlot": -1,
            "DamageLevel": "Functional"
        },
        {
            "MountedLocation": "RightTorso",
            "ComponentDefID": "Ammo_AmmunitionBox_Generic_SRM",
            "ComponentDefType": "AmmunitionBox",
            "HardpointSlot": -1,
            "DamageLevel": "Functional"
        },
        {
            "MountedLocation": "RightTorso",
            "ComponentDefID": "Ammo_AmmunitionBox_Generic_SRM",
            "ComponentDefType": "AmmunitionBox",
            "HardpointSlot": -1,
            "DamageLevel": "Functional"
        },
        {
            "MountedLocation": "RightArm",
            "ComponentDefID": "Weapon_Laser_LargeLaser_0-STOCK",
            "ComponentDefType": "Weapon",
            "HardpointSlot": 0,
            "DamageLevel": "Functional"
        },
        {
            "MountedLocation": "RightArm",
            "ComponentDefID": "Weapon_Laser_MediumLaser_0-STOCK",
            "ComponentDefType": "Weapon",
            "HardpointSlot": 1,
            "DamageLevel": "Functional"
        },
        {
            "MountedLocation": "RightArm",
            "ComponentDefID": "Weapon_Laser_SmallLaser_0-STOCK",
            "ComponentDefType": "Weapon",
            "HardpointSlot": 2,
            "DamageLevel": "Functional"
        },
        {
            "MountedLocation": "LeftLeg",
            "ComponentDefID": "Gear_HeatSink_Generic_Standard",
            "ComponentDefType": "HeatSink",
            "HardpointSlot": -1,
            "DamageLevel": "Functional"
        },
        {
            "MountedLocation": "RightLeg",
            "ComponentDefID": "Gear_HeatSink_Generic_Standard",
            "ComponentDefType": "HeatSink",
            "HardpointSlot": -1,
            "DamageLevel": "Functional"
        }
    ]
}