{
    "MinAppearanceDate": "3048-01-01T00:00:00Z",
    "MechTags": {
        "items": [
            "unit_release",
            "unit_mech",
            "unit_assault",
            "unit_range_short",
            "unit_lance_juggernaut",
            "unit_lance_assassin",
            "unit_role_brawler",
            "unit_speed_high",
            "unit_LosTech",            
            "NotDavion",
            "NotLiao",
            "Marik",
            "NotSteiner",
            "NotKurita",
            "NotComStar",
            "NotMagistracyOfCanopus",
            "NotTaurianConcordat",
            "NotLocals",
            "NotAuriganRestoration",
            "NotAuriganPirates",
            "NotAuriganMercenaries",
            "NotMercenaryReviewBoard",
            "NotKellHounds",
            "NotWolfsDragoons"
        ],
        "tagSetSourceFile": ""
    },
    "ChassisID": "chassisdef_banshee_BNC-3Qr",
    "Description": {
        "Cost": 12740000,
        "Rarity": 4,
        "Purchasable": true,
        "UIName": "Banshee BNC-3Qr",
        "Id": "mechdef_banshee_BNC-3Qr",
        "Name": "Banshee",
        "Details": "A lost tech refit of the Marik exclusive -3Q variant. The heat sinks were upgraded to double, dropping two - enough to handle the increased heat load. Three tons of AC/20 ammo and the small laser were replaced by 4 medium lasers effectivly doubling the potential damage output. Protection was enhanced by installing CASE for proteection the remaining ammo and increasing the armor coverage from 82 percent to 91. The refit was so popular that the original was either upgraded or sold to planetary militias.",
        "Icon": "uixTxrIcon_banshee"
    },
    "simGameMechPartCost": 1274000,
    "Locations": [
        {
            "DamageLevel": "Functional",
            "Location": "Head",
            "CurrentArmor": 45,
            "CurrentRearArmor": -1,
            "CurrentInternalStructure": 16,
            "AssignedArmor": 45,
            "AssignedRearArmor": -1
        },
        {
            "DamageLevel": "Functional",
            "Location": "LeftArm",
            "CurrentArmor": 160,
            "CurrentRearArmor": -1,
            "CurrentInternalStructure": 80,
            "AssignedArmor": 160,
            "AssignedRearArmor": -1
        },
        {
            "DamageLevel": "Functional",
            "Location": "LeftTorso",
            "CurrentArmor": 150,
            "CurrentRearArmor": 50,
            "CurrentInternalStructure": 100,
            "AssignedArmor": 150,
            "AssignedRearArmor": 50
        },
        {
            "DamageLevel": "Functional",
            "Location": "CenterTorso",
            "CurrentArmor": 230,
            "CurrentRearArmor": 55,
            "CurrentInternalStructure": 150,
            "AssignedArmor": 230,
            "AssignedRearArmor": 55
        },
        {
            "DamageLevel": "Functional",
            "Location": "RightTorso",
            "CurrentArmor": 150,
            "CurrentRearArmor": 50,
            "CurrentInternalStructure": 100,
            "AssignedArmor": 150,
            "AssignedRearArmor": 50
        },
        {
            "DamageLevel": "Functional",
            "Location": "RightArm",
            "CurrentArmor": 160,
            "CurrentRearArmor": -1,
            "CurrentInternalStructure": 80,
            "AssignedArmor": 160,
            "AssignedRearArmor": -1
        },
        {
            "DamageLevel": "Functional",
            "Location": "LeftLeg",
            "CurrentArmor": 190,
            "CurrentRearArmor": -1,
            "CurrentInternalStructure": 100,
            "AssignedArmor": 190,
            "AssignedRearArmor": -1
        },
        {
            "DamageLevel": "Functional",
            "Location": "RightLeg",
            "CurrentArmor": 190,
            "CurrentRearArmor": -1,
            "CurrentInternalStructure": 100,
            "AssignedArmor": 190,
            "AssignedRearArmor": -1
        }
    ],
    "inventory": [
        {
            "MountedLocation": "Head",
            "ComponentDefID": "Weapon_Laser_MediumLaser_0-STOCK",
            "ComponentDefType": "Weapon",
            "HardpointSlot": 0,
            "DamageLevel": "Functional"
        },
        {
            "MountedLocation": "LeftTorso",
            "ComponentDefID": "Weapon_Autocannon_AC20_0-STOCK",
            "ComponentDefType": "Weapon",
            "HardpointSlot": 0,
            "DamageLevel": "Functional"
        },
        {
            "MountedLocation": "CenterTorso",
            "ComponentDefID": "Weapon_Laser_MediumLaser_0-STOCK",
            "ComponentDefType": "Weapon",
            "HardpointSlot": 0,
            "DamageLevel": "Functional"
        },
        {
            "MountedLocation": "RightTorso",
            "ComponentDefID": "Weapon_Laser_MediumLaser_0-STOCK",
            "ComponentDefType": "Weapon",
            "HardpointSlot": 0,
            "DamageLevel": "Functional"
        },
        {
            "MountedLocation": "RightTorso",
            "ComponentDefID": "Weapon_Laser_MediumLaser_0-STOCK",
            "ComponentDefType": "Weapon",
            "HardpointSlot": 1,
            "DamageLevel": "Functional"
        },
        {
            "MountedLocation": "RightTorso",
            "ComponentDefID": "Ammo_AmmunitionBox_Generic_AC20",
            "ComponentDefType": "AmmunitionBox",
            "HardpointSlot": -1,
            "DamageLevel": "Functional"
        },
        {
            "MountedLocation": "RightTorso",
            "ComponentDefID": "Ammo_AmmunitionBox_Generic_AC20",
            "ComponentDefType": "AmmunitionBox",
            "HardpointSlot": -1,
            "DamageLevel": "Functional"
        },
        {
            "MountedLocation": "RightTorso",
            "ComponentDefID": "Ammo_AmmunitionBox_Generic_AC20",
            "ComponentDefType": "AmmunitionBox",
            "HardpointSlot": -1,
            "DamageLevel": "Functional"
        }
    ]
}